django_advanced_bulk_signals-0.1.0.dist-info/licenses/LICENSE
django_bulk_signals/__init__.py
django_bulk_signals/decorators.py
django_bulk_signals/managers.py
django_bulk_signals/receivers.py
django_bulk_signals/signals.py
django_bulk_signals/utils.py
django_advanced_bulk_signals-0.1.0.dist-info/METADATA
django_advanced_bulk_signals-0.1.0.dist-info/WHEEL
django_advanced_bulk_signals-0.1.0.dist-info/top_level.txt
django_advanced_bulk_signals-0.1.0.dist-info/RECORD
