Metadata-Version: 2.4
Name: django-advanced-bulk-signals
Version: 0.1.0
Summary: Custom Django signals for update, bulk update/create operations with field tracking
Home-page: https://github.com/jaeger123/django-bulk-signals
Author: Akarsh Sharma
Author-email: akarsh1998@gmail.com
Classifier: Framework :: Django
Classifier: Programming Language :: Python :: 3
Classifier: Operating System :: OS Independent
Classifier: License :: OSI Approved :: MIT License
Requires-Python: >=3.8
License-File: LICENSE
Requires-Dist: Django>=3.2
Dynamic: author
Dynamic: author-email
Dynamic: classifier
Dynamic: description
Dynamic: description-content-type
Dynamic: home-page
Dynamic: license-file
Dynamic: requires-dist
Dynamic: requires-python
Dynamic: summary
